sqrmat_method/__init__.py
sqrmat_method/sqrmat.py
sqrmat_method/sqrmat_method.py
sqrmat_method-0.0.3.dist-info/METADATA
sqrmat_method-0.0.3.dist-info/WHEEL
sqrmat_method-0.0.3.dist-info/licenses/LICENSE
sqrmat_method-0.0.3.dist-info/RECORD
