Metadata-Version: 2.4
Name: sqrmat-method
Version: 0.0.3
Summary: A package for the use of the square matrix method
Project-URL: Bug Tracker, https://github.com/anderske-msu/sqrmat_package/issues
Project-URL: Homepage, https://github.com/anderske-msu/sqrmat_package
Author-email: Kelly Anderson <kjanderson24@proton.me>
License: Copyright 2022 Kelly Anderson
License-File: LICENSE
Requires-Python: >=3.10
Requires-Dist: numpy>=1.2
Requires-Dist: sympy
